{
    "sfide": [
        {
            "nome": "Festa dell'Aria - TRENTO",
            "slug": "festa-povo",
            "attiva": true,
            "weblink": "https://airfriendlyspots.playngo.it",
            "categorie": [
                {
                    "nome": "AriaPovo"
                }
            ],
            "periodo": {
                "dal": "2022-09-19",
                "al": "2022-12-31"
            }
        },
        {
            "nome": "Festa dell'Aria",
            "slug": "festa",
            "attiva": true,
            "weblink": "https://airfriendlyspots.playngo.it",
            "categorie": [
                {
                    "nome": "Aria"
                },
                {
                    "nome": "FerrAria"
                },
                {
                    "nome": "Centraline"
                }
            ],
            "periodo": {
                "dal": "2022-05-04",
                "al": "2022-12-31"
            }
        }
    ]
}